README
setup.py
colorpicker/QColorBarWidget.py
colorpicker/QColorPaletteWidget.py
colorpicker/QColorSetWidget.py
colorpicker/QHueCircleWidget.py
colorpicker/__init__.py
colorpicker.egg-info/PKG-INFO
colorpicker.egg-info/SOURCES.txt
colorpicker.egg-info/dependency_links.txt
colorpicker.egg-info/requires.txt
colorpicker.egg-info/top_level.txt