Metadata-Version: 1.1
Name: colorpicker
Version: 1.1
Summary: Color Picker Widget
Home-page: https://github.com/tokyo-noctambulist/colorpicker
Author: tokyo-noctambulist
Author-email: oohira-k@e-zero1.co.jp
License: MIT License
Keywords: picker,color,palette
Platform: UNKNOWN
Classifier: Development Status :: 4 - Beta
Classifier: Intended Audience :: Developers
Classifier: License :: OSI Approved :: MIT License
Classifier: Natural Language :: English
Classifier: Programming Language :: Python :: 2.7
Classifier: Programming Language :: Python :: 2 :: Only
